deethon/__init__.py
deethon/consts.py
deethon/errors.py
deethon/session.py
deethon/types.py
deethon/utils.py
deethon-0.5.1.dist-info/LICENSE
deethon-0.5.1.dist-info/WHEEL
deethon-0.5.1.dist-info/METADATA
deethon-0.5.1.dist-info/RECORD
