Metadata-Version: 2.1
Name: deethon
Version: 0.5.1
Summary: Python3 library to easily download music from Deezer
Home-page: https://github.com/aykxt/deethon
License: GPL-3.0-or-later
Author: Aykut Yilmaz
Author-email: aykuxt@gmail.com
Maintainer: Aykut Yilmaz
Maintainer-email: aykuxt@gmail.com
Requires-Python: >=3.8,<4.0
Classifier: Development Status :: 3 - Alpha
Classifier: License :: OSI Approved :: GNU General Public License v3 or later (GPLv3+)
Classifier: Operating System :: OS Independent
Classifier: Programming Language :: Python :: 3
Classifier: Programming Language :: Python :: 3.8
Classifier: Programming Language :: Python :: 3.9
Requires-Dist: mutagen (>=1.45.1,<2.0.0)
Requires-Dist: pycryptodome (>=3.10.1,<4.0.0)
Requires-Dist: requests (>=2.25.1,<3.0.0)
Project-URL: Documentation, https://aykxt.github.io/deethon
Project-URL: Repository, https://github.com/aykxt/deethon
